{"_id":"remark-lint-strong-marker","_rev":"1-4ac15985194008d0ed5bdb2d277bc924","name":"remark-lint-strong-marker","description":"remark-lint rule to warn when importance (strong) markers violate the given style","dist-tags":{"latest":"1.0.0"},"versions":{"1.0.0":{"name":"remark-lint-strong-marker","version":"1.0.0","description":"remark-lint rule to warn when importance (strong) markers violate the given style","license":"MIT","keywords":["remark","lint","rule","strong","marker","importance"],"repository":{"type":"git","url":"https://github.com/wooorm/remark-lint/tree/master/packages/remark-lint-strong-marker"},"bugs":{"url":"https://github.com/wooorm/remark-lint/issues"},"author":{"name":"Titus Wormer","email":"tituswormer@gmail.com","url":"http://wooorm.com"},"contributors":[{"name":"Titus Wormer","email":"tituswormer@gmail.com","url":"http://wooorm.com"}],"files":["index.js"],"dependencies":{"unified-lint-rule":"^1.0.0","unist-util-generated":"^1.1.0","unist-util-position":"^3.0.0","unist-util-visit":"^1.1.1"},"xo":false,"_id":"remark-lint-strong-marker@1.0.0","scripts":{},"_shasum":"ce84d0f9336412334f5f29d5c277304d10683eba","_from":".","_npmVersion":"4.0.3","_nodeVersion":"7.0.0","_npmUser":{"name":"wooorm","email":"tituswormer@gmail.com"},"dist":{"shasum":"ce84d0f9336412334f5f29d5c277304d10683eba","tarball":"https://registry.npmjs.org/remark-lint-strong-marker/-/remark-lint-strong-marker-1.0.0.tgz"},"maintainers":[{"name":"wooorm","email":"tituswormer@gmail.com"}],"_npmOperationalInternal":{"host":"packages-18-east.internal.npmjs.com","tmp":"tmp/remark-lint-strong-marker-1.0.0.tgz_1487871104211_0.2737441717181355"},"directories":{}}},"readme":"<!--This file is generated-->\n\n# remark-lint-strong-marker\n\nWarn for violating strong markers.\n\nOptions: `string`, either `'consistent'`, `'*'`, or `'_'`,\ndefault: `'consistent'`.\n\nThe default value, `consistent`, detects the first used strong\nstyle, and will warn when a subsequent strong uses a different\nstyle.\n\n## Install\n\n```sh\nnpm install --save remark-lint-strong-marker\n```\n\n## Example\n\nWhen this rule is turned on, the following file\n`valid.md` is ok:\n\n```markdown\n**foo** and **bar**.\n```\n\nWhen this rule is turned on, the following file\n`also-valid.md` is ok:\n\n```markdown\n__foo__ and __bar__.\n```\n\nWhen this rule is turned on, the following file\n`invalid.md` is **not** ok:\n\n```markdown\n**foo** and __bar__.\n```\n\n```text\n1:13-1:20: Strong should use `*` as a marker\n```\n\nWhen this rule is `'*'`, the following file\n`valid.md` is ok:\n\n```markdown\n**foo**.\n```\n\nWhen this rule is `'_'`, the following file\n`valid.md` is ok:\n\n```markdown\n__foo__.\n```\n\nWhen `'!'` is passed in, the following error is given:\n\n```text\n1:1: Invalid strong marker `!`: use either `'consistent'`, `'*'`, or `'_'`\n```\n\n## License\n\n[MIT](https://github.com/wooorm/remark-lint/blob/master/LICENSE) © [Titus Wormer](http://wooorm.com)\n","maintainers":[{"name":"wooorm","email":"tituswormer@gmail.com"}],"time":{"modified":"2017-02-23T17:31:44.792Z","created":"2017-02-23T17:31:44.792Z","1.0.0":"2017-02-23T17:31:44.792Z"},"keywords":["remark","lint","rule","strong","marker","importance"],"repository":{"type":"git","url":"https://github.com/wooorm/remark-lint/tree/master/packages/remark-lint-strong-marker"},"contributors":[{"name":"Titus Wormer","email":"tituswormer@gmail.com","url":"http://wooorm.com"}],"author":{"name":"Titus Wormer","email":"tituswormer@gmail.com","url":"http://wooorm.com"},"bugs":{"url":"https://github.com/wooorm/remark-lint/issues"},"license":"MIT","readmeFilename":"readme.md","_attachments":{},"_etag":"W/\"58af1c80-e47\"","_lastModified":"Thu, 23 Feb 2017 17:31:44 GMT","_cached":true}